LICENSE
README.md
setup.py
SASpector/SASpector
SASpector/__init__.py
SASpector/coverage.py
SASpector/gene_predict.py
SASpector/kmer.py
SASpector/mapper.py
SASpector/quastunmap.py
SASpector/select_mash.py
SASpector/summary.py
SASpector/tandem_repeats.py
SASpector.egg-info/PKG-INFO
SASpector.egg-info/SOURCES.txt
SASpector.egg-info/dependency_links.txt
SASpector.egg-info/not-zip-safe
SASpector.egg-info/requires.txt
SASpector.egg-info/top_level.txt