Metadata-Version: 2.1
Name: SASpector
Version: 0.0.5
Summary: Short-read Assembly inSpector
Home-page: https://github.com/LoGT-KULeuven/SASpector
Author: KU Leuven
Author-email: alecorrojo@gmail.com, cedric.lood@kuleuven.be
Maintainer: Computational systems biology group
Maintainer-email: vera.vannoort@kuleuven.be
License: UNKNOWN
Platform: UNKNOWN
Classifier: Programming Language :: Python :: 3
Classifier: License :: OSI Approved :: MIT License
Classifier: Operating System :: Unix
Classifier: Operating System :: MacOS :: MacOS X
Requires-Python: >=3.4
License-File: LICENSE
